[{
  "label": "(1-50) Histology of the skin 11-01-22 ",
  "name": "110122quiz",
  "description": "General Knowledge Quiz from 11-01-022",
  "enString" : "en110122",
  "cnString": "cn110122"
}, {
  "label": " (51-100) Histology of the skin 11-01-22 ",
  "name": "110122quiz",
  "description": "General Knowledge Quiz from 11-01-022",
  "enString" : "end110122",
  "cnString": "cnd110122"
},
{
  "label": "(100-150) Replenish 11-02-22",
  "name": "110222quiz",
  "description": "General Knowledge Quiz from 11-02-022",
  "enString" : "en110222",
  "cnString": "cn110222"
}, {
  "label": "(151-212) Replenish 11-02-22",
  "name": "110222quiz",
  "description": "General Knowledge Quiz from 11-02-022",
  "enString" : "end110222",
  "cnString": "cnd110222"
},
{
  "label": "Random 110",
  "name": "110222quiz",
  "description": "General Knowledge Quiz from 11-16-022",
  "enString" : ["en110122", "en110222", "end110122"],
  "cnString": ["cn110122", "cn110222", "cnd110122"],
  "random":true
}]